[{"film_id":"17","title":"Neo Matrix 1","description":"jdkjf","release_year":"55","length":"55","Owner_id":"23","created_at":"0000-00-00 00:00:00"},{"film_id":"18","title":"Neo","description":"dff","release_year":"55","length":"55","Owner_id":"18","created_at":"0000-00-00 00:00:00"},{"film_id":"19","title":"Neo","description":"lk","release_year":"655","length":"66","Owner_id":"18","created_at":"0000-00-00 00:00:00"},{"film_id":"21","title":"Neo","description":"Action","release_year":"1995","length":"120","Owner_id":"23","created_at":"0000-00-00 00:00:00"},{"film_id":"23","title":"Neo","description":"Akce","release_year":"123","length":"120","Owner_id":"18","created_at":"0000-00-00 00:00:00"},{"film_id":"24","title":"Neo","description":"akce","release_year":"2000","length":"120","Owner_id":"23","created_at":"0000-00-00 00:00:00"},{"film_id":"25","title":"Neo","description":"boss","release_year":"1","length":"1","Owner_id":"18","created_at":"0000-00-00 00:00:00"},{"film_id":"27","title":"Neo","description":"sf","release_year":"155","length":"5115","Owner_id":"23","created_at":"0000-00-00 00:00:00"}]